kedro_vertexai/__init__.py
kedro_vertexai/auth/__init__.py
kedro_vertexai/auth/gcp.py
kedro_vertexai/auth/mlflow_request_header_provider.py
kedro_vertexai/auth/mlflow_request_header_provider_hook.py
kedro_vertexai/cli.py
kedro_vertexai/client.py
kedro_vertexai/config.py
kedro_vertexai/constants.py
kedro_vertexai/context_helper.py
kedro_vertexai/dynamic_config.py
kedro_vertexai/generator.py
kedro_vertexai/grouping.py
kedro_vertexai/hooks.py
kedro_vertexai/templates/github-on-push.yml
kedro_vertexai/utils.py
kedro_vertexai/vertex_ai/__init__.py
kedro_vertexai/vertex_ai/datasets.py
kedro_vertexai/vertex_ai/runner.py
kedro_vertexai-1.0.0.dist-info/LICENSE
kedro_vertexai-1.0.0.dist-info/METADATA
kedro_vertexai-1.0.0.dist-info/WHEEL
kedro_vertexai-1.0.0.dist-info/entry_points.txt
kedro_vertexai-1.0.0.dist-info/RECORD
