Metadata-Version: 2.3
Name: kedro-vertexai
Version: 1.0.0
Summary: Kedro plugin with GCP Vertex AI support
License: Apache-2.0
Keywords: kedro-plugin,kedro,mlops,vertexai,googlecloudplatform,machinelearning
Author: Marcin Zabłocki
Author-email: marcin.zablocki@getindata.com
Maintainer: GetInData MLOPS
Maintainer-email: mlops@getindata.com
Requires-Python: >=3.10,<3.13
Classifier: Development Status :: 4 - Beta
Classifier: License :: OSI Approved :: Apache Software License
Classifier: Programming Language :: Python :: 3
Classifier: Programming Language :: Python :: 3.10
Classifier: Programming Language :: Python :: 3.11
Classifier: Programming Language :: Python :: 3.12
Provides-Extra: mlflow
Requires-Dist: cachetools (>=3.0,<6.0)
Requires-Dist: click (>=8.0.4)
Requires-Dist: cloudpickle (>=3.0.0,<4.0.0)
Requires-Dist: fsspec (>=2022.1)
Requires-Dist: gcsfs (>=2022.1)
Requires-Dist: google-auth (<3)
Requires-Dist: google-cloud-aiplatform[metadata] (>=1.59.0,<2.0.0)
Requires-Dist: google-cloud-iam (<3)
Requires-Dist: google-cloud-scheduler (>=2.3.2)
Requires-Dist: google-cloud-storage (<3.0.0)
Requires-Dist: grpcio (>=1.4.0,<2.0.0)
Requires-Dist: grpcio-status (>=1.4.0,<2.0.0)
Requires-Dist: kedro (>=1.0.0,<2.0.0)
Requires-Dist: kedro-mlflow (>=1.0.0,<2.0.0) ; extra == "mlflow"
Requires-Dist: kfp (>=2.0.0,<2.9.0)
Requires-Dist: makefun (>=1.15.6,<2.0.0)
Requires-Dist: mlflow (>=2.14.3,<3.0)
Requires-Dist: protobuf (>=3.18.0,<21.0)
Requires-Dist: pyarrow (>=14.0.1)
Requires-Dist: pydantic (>=2,<3)
Requires-Dist: semver (>=2.10,<4.0.0)
Requires-Dist: tabulate (>=0.8.7)
Requires-Dist: toposort (>1.0,<2.0)
Project-URL: Documentation, https://kedro-vertexai.readthedocs.io/
Project-URL: Homepage, https://github.com/getindata/kedro-vertexai
Project-URL: Repository, https://github.com/getindata/kedro-vertexai
